sentrial/__init__.py
sentrial/async_client.py
sentrial/client.py
sentrial/decorators.py
sentrial/langchain.py
sentrial/otel.py
sentrial/py.typed
sentrial/types.py
sentrial/wrappers.py
sentrial-0.4.2.dist-info/licenses/LICENSE
sentrial-0.4.2.dist-info/METADATA
sentrial-0.4.2.dist-info/WHEEL
sentrial-0.4.2.dist-info/top_level.txt
sentrial-0.4.2.dist-info/RECORD
