Metadata-Version: 2.4
Name: sentrial
Version: 0.4.2
Summary: Sentrial - Performance monitoring and observability for AI agents
Author-email: Sentrial Team <support@sentrial.ai>
License: MIT
Project-URL: Homepage, https://sentrial.com
Project-URL: Documentation, https://docs.sentrial.com
Project-URL: Repository, https://github.com/neelshar/sentrial
Project-URL: Bug Tracker, https://github.com/neelshar/sentrial/issues
Keywords: ai,agents,observability,debugging,langchain,llm,openai,anthropic,gemini
Classifier: Development Status :: 4 - Beta
Classifier: Intended Audience :: Developers
Classifier: License :: OSI Approved :: MIT License
Classifier: Programming Language :: Python :: 3
Classifier: Programming Language :: Python :: 3.8
Classifier: Programming Language :: Python :: 3.9
Classifier: Programming Language :: Python :: 3.10
Classifier: Programming Language :: Python :: 3.11
Classifier: Programming Language :: Python :: 3.12
Classifier: Topic :: Software Development :: Libraries :: Python Modules
Classifier: Topic :: Scientific/Engineering :: Artificial Intelligence
Requires-Python: >=3.8
License-File: LICENSE
Requires-Dist: requests>=2.31.0
Provides-Extra: openai
Requires-Dist: openai>=1.0.0; extra == "openai"
Provides-Extra: anthropic
Requires-Dist: anthropic>=0.18.0; extra == "anthropic"
Provides-Extra: google
Requires-Dist: google-generativeai>=0.4.0; extra == "google"
Provides-Extra: async
Requires-Dist: httpx>=0.25.0; extra == "async"
Provides-Extra: otel
Requires-Dist: opentelemetry-api>=1.20.0; extra == "otel"
Requires-Dist: opentelemetry-sdk>=1.20.0; extra == "otel"
Provides-Extra: langchain
Requires-Dist: langchain>=1.0.0; extra == "langchain"
Requires-Dist: langchain-core>=0.3.0; extra == "langchain"
Requires-Dist: langchain-openai>=0.2.0; extra == "langchain"
Requires-Dist: langchain-google-genai>=4.0.0; extra == "langchain"
Requires-Dist: langchain-anthropic>=0.2.0; extra == "langchain"
Provides-Extra: dev
Requires-Dist: pytest>=7.4.0; extra == "dev"
Requires-Dist: black>=23.0.0; extra == "dev"
Requires-Dist: mypy>=1.5.0; extra == "dev"
Requires-Dist: ruff>=0.1.0; extra == "dev"
Provides-Extra: providers
Requires-Dist: openai>=1.0.0; extra == "providers"
Requires-Dist: anthropic>=0.18.0; extra == "providers"
Requires-Dist: google-generativeai>=0.4.0; extra == "providers"
Provides-Extra: all
Requires-Dist: openai>=1.0.0; extra == "all"
Requires-Dist: anthropic>=0.18.0; extra == "all"
Requires-Dist: google-generativeai>=0.4.0; extra == "all"
Requires-Dist: httpx>=0.25.0; extra == "all"
Requires-Dist: opentelemetry-api>=1.20.0; extra == "all"
Requires-Dist: opentelemetry-sdk>=1.20.0; extra == "all"
Requires-Dist: langchain>=1.0.0; extra == "all"
Requires-Dist: langchain-core>=0.3.0; extra == "all"
Requires-Dist: langchain-openai>=0.2.0; extra == "all"
Requires-Dist: langchain-google-genai>=4.0.0; extra == "all"
Requires-Dist: langchain-anthropic>=0.2.0; extra == "all"
Dynamic: license-file
